README.rst
setup.py
jdsgreeter/__init__.py
jdsgreeter/greeter.py
jdsgreeter.egg-info/PKG-INFO
jdsgreeter.egg-info/SOURCES.txt
jdsgreeter.egg-info/dependency_links.txt
jdsgreeter.egg-info/top_level.txt