Metadata-Version: 1.0
Name: jdsgreeter
Version: 0.0.1
Summary: a pip-installable package example
Home-page: https://github.com/johndsheehan/greeter
Author: John D Sheehan
Author-email: john.d.sheehan@gmail.com
License: MIT
Keywords: example
Platform: UNKNOWN
